[
 {
  "developer_reputation": 0.0,
  "bug_severity": null,
  "bugfix_time": null,
  "attachments": 0,
  "dependencies": 0,
  "nr_of_developers": 4
 },
 {
  "developer_reputation": 0.0,
  "bug_severity": null,
  "bugfix_time": null,
  "attachments": 0,
  "dependencies": 0,
  "nr_of_developers": 4
 },
 {
  "developer_reputation": 0.0,
  "bug_severity": null,
  "bugfix_time": null,
  "attachments": 0,
  "dependencies": 0,
  "nr_of_developers": 4
 },
 {
  "developer_reputation": 0.0,
  "bug_severity": null,
  "bugfix_time": null,
  "attachments": 0,
  "dependencies": 0,
  "nr_of_developers": 8
 },
 {
  "developer_reputation": 0.0,
  "bug_severity": null,
  "bugfix_time": null,
  "attachments": 0,
  "dependencies": 0,
  "nr_of_developers": 7
 },
 {
  "developer_reputation": 0.034482758620689655,
  "bug_severity": null,
  "bugfix_time": null,
  "attachments": 0,
  "dependencies": 0,
  "nr_of_developers": 4
 },
 {
  "developer_reputation": 0.31316725978647686,
  "bug_severity": null,
  "bugfix_time": null,
  "attachments": 0,
  "dependencies": 0,
  "nr_of_developers": 5
 },
 {
  "developer_reputation": 0.0,
  "bug_severity": null,
  "bugfix_time": null,
  "attachments": 0,
  "dependencies": 0,
  "nr_of_developers": 3
 },
 {
  "developer_reputation": 0.0,
  "bug_severity": 5,
  "bugfix_time": 669,
  "attachments": 1,
  "dependencies": 2,
  "nr_of_developers": 9
 },
 {
  "developer_reputation": 0.025,
  "bug_severity": null,
  "bugfix_time": null,
  "attachments": 0,
  "dependencies": 0,
  "nr_of_developers": 4
 },
 {
  "developer_reputation": 0.0026595744680851063,
  "bug_severity": null,
  "bugfix_time": null,
  "attachments": 0,
  "dependencies": 0,
  "nr_of_developers": 4
 },
 {
  "developer_reputation": 0.0,
  "bug_severity": null,
  "bugfix_time": null,
  "attachments": 0,
  "dependencies": 0,
  "nr_of_developers": 6
 },
 {
  "developer_reputation": 0.0,
  "bug_severity": null,
  "bugfix_time": null,
  "attachments": 0,
  "dependencies": 0,
  "nr_of_developers": 6
 },
 {
  "developer_reputation": 0.0,
  "bug_severity": null,
  "bugfix_time": null,
  "attachments": 0,
  "dependencies": 0,
  "nr_of_developers": 5
 },
 {
  "developer_reputation": 0.0,
  "bug_severity": 4,
  "bugfix_time": 73,
  "attachments": 2,
  "dependencies": 2,
  "nr_of_developers": 4
 },
 {
  "developer_reputation": 0.034482758620689655,
  "bug_severity": null,
  "bugfix_time": null,
  "attachments": 0,
  "dependencies": 0,
  "nr_of_developers": 4
 },
 {
  "developer_reputation": 0.02702702702702703,
  "bug_severity": null,
  "bugfix_time": null,
  "attachments": 0,
  "dependencies": 0,
  "nr_of_developers": 7
 },
 {
  "developer_reputation": 0.0024813895781637717,
  "bug_severity": 1,
  "bugfix_time": 579,
  "attachments": 3,
  "dependencies": 2,
  "nr_of_developers": 15
 },
 {
  "developer_reputation": 0.0,
  "bug_severity": null,
  "bugfix_time": null,
  "attachments": 0,
  "dependencies": 0,
  "nr_of_developers": 6
 },
 {
  "developer_reputation": 0.0,
  "bug_severity": null,
  "bugfix_time": null,
  "attachments": 0,
  "dependencies": 0,
  "nr_of_developers": 3
 },
 {
  "developer_reputation": 0.0,
  "bug_severity": null,
  "bugfix_time": null,
  "attachments": 0,
  "dependencies": 0,
  "nr_of_developers": 3
 },
 {
  "developer_reputation": 0.02857142857142857,
  "bug_severity": null,
  "bugfix_time": null,
  "attachments": 0,
  "dependencies": 0,
  "nr_of_developers": 2
 },
 {
  "developer_reputation": 0.37373737373737376,
  "bug_severity": 4,
  "bugfix_time": 36,
  "attachments": 1,
  "dependencies": 3,
  "nr_of_developers": 12
 },
 {
  "developer_reputation": 0.0,
  "bug_severity": 4,
  "bugfix_time": 172,
  "attachments": 2,
  "dependencies": 3,
  "nr_of_developers": 5
 },
 {
  "developer_reputation": 0.0,
  "bug_severity": 4,
  "bugfix_time": 270,
  "attachments": 1,
  "dependencies": 4,
  "nr_of_developers": 3
 },
 {
  "developer_reputation": 0.0,
  "bug_severity": 4,
  "bugfix_time": 70,
  "attachments": 1,
  "dependencies": 3,
  "nr_of_developers": 4
 },
 {
  "developer_reputation": 0.034482758620689655,
  "bug_severity": null,
  "bugfix_time": null,
  "attachments": 0,
  "dependencies": 0,
  "nr_of_developers": 2
 },
 {
  "developer_reputation": 0.0,
  "bug_severity": 3,
  "bugfix_time": 0,
  "attachments": 2,
  "dependencies": 2,
  "nr_of_developers": 4
 },
 {
  "developer_reputation": 0.0,
  "bug_severity": null,
  "bugfix_time": null,
  "attachments": 0,
  "dependencies": 0,
  "nr_of_developers": 4
 },
 {
  "developer_reputation": 0.0,
  "bug_severity": null,
  "bugfix_time": null,
  "attachments": 0,
  "dependencies": 0,
  "nr_of_developers": 3
 },
 {
  "developer_reputation": 0.08849557522123894,
  "bug_severity": 4,
  "bugfix_time": 11,
  "attachments": 1,
  "dependencies": 3,
  "nr_of_developers": 7
 },
 {
  "developer_reputation": 0.02857142857142857,
  "bug_severity": 4,
  "bugfix_time": 27,
  "attachments": 1,
  "dependencies": 2,
  "nr_of_developers": 3
 },
 {
  "developer_reputation": 0.0,
  "bug_severity": 4,
  "bugfix_time": 2,
  "attachments": 1,
  "dependencies": 2,
  "nr_of_developers": 4
 },
 {
  "developer_reputation": 0.09230769230769231,
  "bug_severity": 6,
  "bugfix_time": 136,
  "attachments": 1,
  "dependencies": 3,
  "nr_of_developers": 10
 },
 {
  "developer_reputation": 0.0,
  "bug_severity": 4,
  "bugfix_time": 64,
  "attachments": 2,
  "dependencies": 2,
  "nr_of_developers": 5
 },
 {
  "developer_reputation": 0.0,
  "bug_severity": 4,
  "bugfix_time": 71,
  "attachments": 1,
  "dependencies": 2,
  "nr_of_developers": 6
 },
 {
  "developer_reputation": 0.22413793103448276,
  "bug_severity": 6,
  "bugfix_time": 525,
  "attachments": 1,
  "dependencies": 4,
  "nr_of_developers": 13
 },
 {
  "developer_reputation": 0.0,
  "bug_severity": null,
  "bugfix_time": null,
  "attachments": 0,
  "dependencies": 0,
  "nr_of_developers": 1
 },
 {
  "developer_reputation": 0.0,
  "bug_severity": null,
  "bugfix_time": null,
  "attachments": 0,
  "dependencies": 0,
  "nr_of_developers": 2
 },
 {
  "developer_reputation": 0.02702702702702703,
  "bug_severity": null,
  "bugfix_time": null,
  "attachments": 0,
  "dependencies": 0,
  "nr_of_developers": 14
 },
 {
  "developer_reputation": 0.02857142857142857,
  "bug_severity": null,
  "bugfix_time": null,
  "attachments": 0,
  "dependencies": 0,
  "nr_of_developers": 3
 },
 {
  "developer_reputation": 0.0,
  "bug_severity": 5,
  "bugfix_time": 149,
  "attachments": 1,
  "dependencies": 2,
  "nr_of_developers": 7
 },
 {
  "developer_reputation": 0.0,
  "bug_severity": 3,
  "bugfix_time": 30,
  "attachments": 1,
  "dependencies": 2,
  "nr_of_developers": 2
 },
 {
  "developer_reputation": 0.0,
  "bug_severity": null,
  "bugfix_time": null,
  "attachments": 0,
  "dependencies": 0,
  "nr_of_developers": 7
 },
 {
  "developer_reputation": 0.0,
  "bug_severity": 4,
  "bugfix_time": 153,
  "attachments": 1,
  "dependencies": 2,
  "nr_of_developers": 6
 }
]